lcservice/__init__.py
lcservice/jobs.py
lcservice/service.py
lcservice/simulator.py
lcservice/servers/__init__.py
lcservice/servers/cherrypy.py
lcservice/servers/cloud_function.py
lcservice-1.8.6.dist-info/LICENSE
lcservice-1.8.6.dist-info/METADATA
lcservice-1.8.6.dist-info/WHEEL
lcservice-1.8.6.dist-info/top_level.txt
lcservice-1.8.6.dist-info/zip-safe
lcservice-1.8.6.dist-info/RECORD
