Metadata-Version: 2.1
Name: lcservice
Version: 1.8.6
Summary: Reference implementation for LimaCharlie.io services.
Home-page: https://limacharlie.io
Author: Maxime Lamothe-Brassard ( Refraction Point, Inc )
Author-email: maxime@refractionpoint.com
License: Apache v2
Platform: UNKNOWN
Requires-Dist: cherrypy
Requires-Dist: limacharlie
Requires-Dist: pyyaml
